straindesign/__init__.py
straindesign/compute_strain_designs.py
straindesign/cplex_interface.py
straindesign/efmtool.jar
straindesign/efmtool.py
straindesign/glpk_interface.py
straindesign/gurobi_interface.py
straindesign/indicatorConstraints.py
straindesign/lptools.py
straindesign/names.py
straindesign/networktools.py
straindesign/parse_constr.py
straindesign/pool.py
straindesign/scip_interface.py
straindesign/solver_interface.py
straindesign/strainDesignMILP.py
straindesign/strainDesignModule.py
straindesign/strainDesignProblem.py
straindesign/strainDesignSolutions.py
straindesign-1.15.dist-info/licenses/LICENSE
tests/__init__.py
tests/conftest.py
tests/custom.py
tests/test_01_load_models_and_solvers.py
tests/test_02_lp_optimization.py
tests/test_03_plots.py
tests/test_04_preprocessing.py
tests/test_05_straindesign.py
tests/test_06_multiprocessing.py
straindesign-1.15.dist-info/METADATA
straindesign-1.15.dist-info/WHEEL
straindesign-1.15.dist-info/top_level.txt
straindesign-1.15.dist-info/RECORD
