Metadata-Version: 2.4
Name: straindesign
Version: 1.15
Summary: Computational strain design package for the COBRApy framework
Home-page: https://github.com/klamt-lab/straindesign.git
Author: Philipp Schneider
Author-email: zgddtgt@gmail.com
License: Apache License 2.0
Project-URL: Bug Reports, https://github.com/klamt-lab/straindesign/issues
Project-URL: Source, https://github.com/klamt-lab/straindesign/
Project-URL: Documentation, https://straindesign.readthedocs.io/en/latest/index.html
Keywords: metabolism,constraint-based,mixed-integer,strain design
Classifier: Intended Audience :: Science/Research
Classifier: Development Status :: 3 - Alpha
Classifier: Programming Language :: Python :: 3.9
Classifier: Programming Language :: Python :: 3.10
Classifier: Programming Language :: Python :: 3.11
Classifier: Programming Language :: Python :: 3.12
Classifier: Natural Language :: English
Classifier: Operating System :: OS Independent
Classifier: Topic :: Scientific/Engineering :: Bio-Informatics
Requires-Python: >=3.7
License-File: LICENSE
Requires-Dist: cobra
Requires-Dist: jpype1
Requires-Dist: scipy
Requires-Dist: matplotlib
Requires-Dist: psutil
Dynamic: author
Dynamic: author-email
Dynamic: classifier
Dynamic: description
Dynamic: description-content-type
Dynamic: home-page
Dynamic: keywords
Dynamic: license
Dynamic: license-file
Dynamic: project-url
Dynamic: requires-dist
Dynamic: requires-python
Dynamic: summary
